torchflint/__init__.py
torchflint/functional.py
torchflint/image/__init__.py
torchflint/image/functional.py
torchflint/nn/__init__.py
torchflint/nn/buffer.py
torchflint/nn/buffer.pyi
torchflint/nn/functional.py
torchflint/nn/module.py
torchflint/patchwork/__init__.py
torchflint/patchwork/convolution.py
torchflint/patchwork/patches.py
torchflint/patchwork/pooling.py
torchflint/utils/__init__.py
torchflint/utils/_helper.py
torchflint/utils/_masked.py
torchflint/utils/compilable.py
torchflint/utils/devices.py
torchflint/utils/typing.py
torchflint-0.0.1b16.post1.dev3.dist-info/licenses/LICENSE
torchflint-0.0.1b16.post1.dev3.dist-info/METADATA
torchflint-0.0.1b16.post1.dev3.dist-info/WHEEL
torchflint-0.0.1b16.post1.dev3.dist-info/top_level.txt
torchflint-0.0.1b16.post1.dev3.dist-info/RECORD
