Metadata-Version: 2.4
Name: torchflint
Version: 0.0.1b16.post1.dev3
Summary: TorchFlint is a collection of advanced utility functions designed for tensor manipulation within the PyTorch ecosystem. It provides granular control over high-dimensional data processing, bridging the gap between high-level neural modules and low-level tensor operations.
Author-email: Caewinix <Caewinix@yeah.net>
Project-URL: Homepage, https://github.com/Caewinix/torchflint
Project-URL: Bug Tracker, https://github.com/Caewinix/torchflint/issues
Classifier: Programming Language :: Python :: 3
Classifier: License :: OSI Approved :: MIT License
Classifier: Operating System :: OS Independent
Requires-Python: >=3.7
License-File: LICENSE
Requires-Dist: torch>=1.6.0
Requires-Dist: torchvision
Requires-Dist: pyreflex>=0.0.1b13
Dynamic: license-file
